simpleunit/__init__.py
simpleunit/unit_simple.py
simpleunit-1.0.30.dist-info/LICENSE.md
simpleunit-1.0.30.dist-info/METADATA
simpleunit-1.0.30.dist-info/WHEEL
simpleunit-1.0.30.dist-info/top_level.txt
simpleunit-1.0.30.dist-info/RECORD
