Metadata-Version: 2.2
Name: simpleunit
Version: 1.0.30
Summary: A simple measurement unit API to handle basic unit conversions.
Author-email: Samuel Andrés <samuel.andres@yahoo.fr>
License: This is free and unencumbered software released into the public domain.
Project-URL: Homepage, https://github.com/SamuelAndresPascal/cosmoloj-py/tree/simpleunit_1.0.30/simpleunit
Project-URL: Documentation, http://cosmoloj.com/mkdocs/simpleunit/1.0.30
Project-URL: Specification, http://cosmoloj.com/su
Keywords: units,converter,unit converter,measure,units of measurement
Classifier: Programming Language :: Python :: 3
Classifier: Operating System :: OS Independent
Classifier: Development Status :: 5 - Production/Stable
Classifier: Intended Audience :: Developers
Classifier: Intended Audience :: Science/Research
Classifier: License :: Public Domain
Classifier: Topic :: Scientific/Engineering
Classifier: Topic :: Software Development
Classifier: Topic :: Utilities
Requires-Python: >=3.7
License-File: LICENSE.md
